streamlit_kanban_board_goviceversa/__init__.py
streamlit_kanban_board_goviceversa/frontend/build/asset-manifest.json
streamlit_kanban_board_goviceversa/frontend/build/index.html
streamlit_kanban_board_goviceversa/frontend/build/static/css/main.164025da.css
streamlit_kanban_board_goviceversa/frontend/build/static/css/main.164025da.css.map
streamlit_kanban_board_goviceversa/frontend/build/static/js/main.683298de.js
streamlit_kanban_board_goviceversa/frontend/build/static/js/main.683298de.js.LICENSE.txt
streamlit_kanban_board_goviceversa/frontend/build/static/js/main.683298de.js.map
streamlit_kanban_board_goviceversa-1.2.1.dist-info/licenses/LICENSE
streamlit_kanban_board_goviceversa-1.2.1.dist-info/METADATA
streamlit_kanban_board_goviceversa-1.2.1.dist-info/WHEEL
streamlit_kanban_board_goviceversa-1.2.1.dist-info/top_level.txt
streamlit_kanban_board_goviceversa-1.2.1.dist-info/RECORD
