Metadata-Version: 2.4
Name: streamlit-kanban-board-goviceversa
Version: 1.2.1
Summary: A powerful, interactive Kanban board component for Streamlit applications with drag-and-drop functionality, DLA V2 pre-computed permissions, and customizable workflows.
Author-email: Pierluigi Segatto <pier@goviceversa.com>
License: MIT
Project-URL: Homepage, https://github.com/goviceversa-com/streamlit_kanban_board
Project-URL: Repository, https://github.com/goviceversa-com/streamlit_kanban_board
Project-URL: Documentation, https://github.com/goviceversa-com/streamlit_kanban_board#readme
Project-URL: Bug Tracker, https://github.com/goviceversa-com/streamlit_kanban_board/issues
Project-URL: Funding, https://github.com/sponsors/pierluigisegatto
Keywords: streamlit,kanban,board,drag-drop,workflow,pipeline,project-management
Classifier: Development Status :: 4 - Beta
Classifier: Intended Audience :: Developers
Classifier: Intended Audience :: Financial and Insurance Industry
Classifier: Intended Audience :: Information Technology
Classifier: License :: OSI Approved :: MIT License
Classifier: Programming Language :: Python :: 3
Classifier: Programming Language :: Python :: 3.9
Classifier: Programming Language :: Python :: 3.10
Classifier: Programming Language :: Python :: 3.11
Classifier: Programming Language :: Python :: 3.12
Classifier: Topic :: Office/Business :: Financial
Classifier: Topic :: Office/Business :: Groupware
Classifier: Topic :: Software Development :: Libraries :: Python Modules
Classifier: Topic :: Software Development :: User Interfaces
Requires-Python: >=3.9
License-File: LICENSE
Requires-Dist: streamlit>=1.0.0
Dynamic: license-file
